easywindcss/__init__.py
easywindcss/main.py
easywindcss-1.5.dist-info/METADATA
easywindcss-1.5.dist-info/WHEEL
easywindcss-1.5.dist-info/entry_points.txt
easywindcss-1.5.dist-info/top_level.txt
easywindcss-1.5.dist-info/RECORD
