Metadata-Version: 2.1
Name: easywindcss
Version: 1.5
Summary: A Python library to automate Tailwind CSS setup in your python environment.
Author: Sayed Afaq
Requires-Python: >=3.6
Requires-Dist: colorama
